src/Polly.py
src/TerminalChat.py
src/Test.py
src/WindowChat.py
src/__init__.py
AudioChatGpt-0.11.dist-info/METADATA
AudioChatGpt-0.11.dist-info/WHEEL
AudioChatGpt-0.11.dist-info/top_level.txt
AudioChatGpt-0.11.dist-info/RECORD
