Metadata-Version: 2.1
Name: AudioChatGpt
Version: 0.11
Summary: A simple project to make ChatGpt speak
Home-page: https://spreadyourwings@dev.azure.com/spreadyourwings/spreadyourwings/_git/AudioChatGpt_Py
Author: Alexander Popovic
Author-email: apopovic.aut@gmail.com
Classifier: Development Status :: 3 - Alpha
Classifier: License :: OSI Approved :: MIT License
Classifier: Programming Language :: Python :: 3.11
Classifier: Programming Language :: Python :: 3.10
